analytics/test/__init__.py
analytics/test/test_client.py
eventbridge/analytics/__init__.py
eventbridge/analytics/client.py
eventbridge/analytics/consumer.py
eventbridge/analytics/request.py
eventbridge/analytics/utils.py
eventbridge/analytics/version.py
eventbridge_analytics_python-2.2.5.dist-info/LICENSE
eventbridge_analytics_python-2.2.5.dist-info/METADATA
eventbridge_analytics_python-2.2.5.dist-info/WHEEL
eventbridge_analytics_python-2.2.5.dist-info/top_level.txt
eventbridge_analytics_python-2.2.5.dist-info/RECORD
